aws_feature_store/__init__.py
aws_feature_store/feature_definition.py
aws_feature_store/feature_group.py
aws_feature_store/inputs.py
aws_feature_store-0.0.17.dist-info/LICENSE
aws_feature_store-0.0.17.dist-info/METADATA
aws_feature_store-0.0.17.dist-info/WHEEL
aws_feature_store-0.0.17.dist-info/top_level.txt
aws_feature_store-0.0.17.dist-info/RECORD
