Metadata-Version: 2.1
Name: aws-feature-store
Version: 0.0.17
Summary: Simplified SageMaker Feature Store
Home-page: https://github.com/bilykigor/aws_feature_store
Author: Ihor Bilyk
License: Apache License 2.0
Keywords: Simplified SageMaker Feature Store
Classifier: Development Status :: 5 - Production/Stable
Classifier: Intended Audience :: Developers
Classifier: Natural Language :: English
Classifier: License :: OSI Approved :: Apache Software License
Classifier: Programming Language :: Python
Classifier: Programming Language :: Python :: 3.7
Classifier: Programming Language :: Python :: 3.8
Classifier: Programming Language :: Python :: 3.9
Classifier: Programming Language :: Python :: 3.10
Requires-Python: >= 3.6
License-File: LICENSE
Requires-Dist: boto3 (<2.0,>=1.20.21)
Requires-Dist: pandas
